summawise/__init__.py
summawise/__main__.py
summawise/ai.py
summawise/data.py
summawise/errors.py
summawise/main.py
summawise/serializable.py
summawise/settings.py
summawise/web.py
summawise/youtube.py
summawise/api_objects/__init__.py
summawise/api_objects/assistants.py
summawise/api_objects/generic.py
summawise/api_objects/threads.py
summawise/commands/__init__.py
summawise/commands/assistants.py
summawise/commands/scan.py
summawise/commands/threads.py
summawise/files/cache.py
summawise/files/encodings.py
summawise/files/metadata.py
summawise/files/processing.py
summawise/files/utils.py
summawise/utils/__init__.py
summawise/utils/misc.py
summawise/utils/terminal.py
summawise/utils/validators.py
summawise-0.5.5.dist-info/METADATA
summawise-0.5.5.dist-info/WHEEL
summawise-0.5.5.dist-info/entry_points.txt
summawise-0.5.5.dist-info/licenses/LICENSE
summawise-0.5.5.dist-info/RECORD
