Metadata-Version: 2.3
Name: summawise
Version: 0.5.5
Summary: Summarize information from vectorized files using OpenAI's powerful models, and explore data further with an interactive prompt for deep dives into content.
Project-URL: Homepage, https://github.com/ooojustin/summawise
Project-URL: Documentation, https://github.com/ooojustin/summawise#readme
Project-URL: Source, https://github.com/ooojustin/summawise
Project-URL: Tracker, https://github.com/ooojustin/summawise/issues
Project-URL: Changelog, https://github.com/ooojustin/summawise/blob/main/CHANGELOG.md
Author-email: Justin Garofolo <justin@garofolo.net>
License: GPLv3
License-File: LICENSE
Classifier: Development Status :: 4 - Beta
Classifier: Intended Audience :: Developers
Classifier: Intended Audience :: Education
Classifier: Intended Audience :: End Users/Desktop
Classifier: Intended Audience :: Science/Research
Classifier: License :: OSI Approved :: GNU General Public License v3 (GPLv3)
Classifier: Programming Language :: Python :: 3.8
Classifier: Programming Language :: Python :: 3.9
Classifier: Programming Language :: Python :: 3.10
Classifier: Programming Language :: Python :: 3.11
Classifier: Programming Language :: Python :: 3.12
Classifier: Topic :: Scientific/Engineering :: Artificial Intelligence
Classifier: Topic :: Scientific/Engineering :: Information Analysis
Classifier: Topic :: Text Processing :: General
Classifier: Typing :: Typed
Requires-Python: >=3.8
Requires-Dist: openai>=1.35.0
Requires-Dist: requests>=2.32.0
Requires-Dist: validators>=0.28.0
Requires-Dist: youtube-transcript-api>=0.6.0
